shape/game_logic.py
shape/main.py
shape/utils.py
shape/katago/analysis.cfg
shape/katago/downloader.py
shape/katago/engine.py
shape/ui/board_view.py
shape/ui/main_window.py
shape/ui/tab_analysis.py
shape/ui/tab_config.py
shape/ui/tab_main_control.py
shape/ui/ui_utils.py
goshape-0.2.0.dist-info/METADATA
goshape-0.2.0.dist-info/WHEEL
goshape-0.2.0.dist-info/entry_points.txt
goshape-0.2.0.dist-info/licenses/LICENSE
goshape-0.2.0.dist-info/RECORD
