Metadata-Version: 2.4
Name: goshape
Version: 0.2.0
Summary: Shape Habits Analysis and Personalized Evaluation
Author: Sander Land
License-File: LICENSE
Requires-Python: <3.14,>=3.10
Requires-Dist: httpx>=0.25.0
Requires-Dist: matplotlib>=3.5.0
Requires-Dist: numpy>=2.1.2
Requires-Dist: pysgf>=0.9.0
Requires-Dist: pyside6>=6.5.0
